odoo_launcher/__init__.py
odoo_launcher/api.py
odoo_launcher/config_section.py
odoo_launcher/laucher.py
odoo_launcher/mapper.py
odoo_launcher/odoo_config_maker.py
odoo_launcher-1.3.4.dist-info/METADATA
odoo_launcher-1.3.4.dist-info/WHEEL
odoo_launcher-1.3.4.dist-info/top_level.txt
odoo_launcher-1.3.4.dist-info/RECORD
