Metadata-Version: 2.1
Name: odoo-launcher
Version: 1.3.4
Summary: Create config compatible with Odoo
Home-page: https://gitlab.ndp-systemes.fr/python-libs/odoo_launcher
Author: Alexis Pasquier, NDP Systemes
Author-email: opensource@ndp-systemes.fr
License: GPLv3
Classifier: Programming Language :: Python :: 2
Classifier: Programming Language :: Python :: 2.7
Classifier: Programming Language :: Python :: 3
Classifier: Programming Language :: Python :: 3.6
Classifier: Programming Language :: Python :: 3.7
Classifier: Programming Language :: Python :: 3.8
Classifier: Programming Language :: Python :: 3.9
Classifier: Programming Language :: Python :: 3.10
Requires-Python: !=3.0.*,!=3.1.*,!=3.2.*,!=3.3.*,!=3.4.*,!=3.5.*,>=2.7
Requires-Dist: addons-installer (<2,>=1.4.1)
Requires-Dist: maintenance-server (<2,>=1.2.1)
Requires-Dist: enum34 (==1.1.10) ; python_version <= "3"
Requires-Dist: typing (==3.10.0.0) ; python_version <= "3"
